setup.py
pymongohandler/__init__.py
pymongohandler.egg-info/PKG-INFO
pymongohandler.egg-info/SOURCES.txt
pymongohandler.egg-info/dependency_links.txt
pymongohandler.egg-info/not-zip-safe
pymongohandler.egg-info/top_level.txt