Metadata-Version: 1.0
Name: pymongohandler
Version: 0.1
Summary: A wrapper for Python & mongoDB
Home-page: https://gitlab.atc.gr/reveal/pymongohandler.git
Author: Giorgos Giotis
Author-email: g.giotis@atc.gr
License: MIT
Platform: UNKNOWN
